[{"title":"Divya","body":"Likes Node"},{"title":"Dheeraj","body":"Likes Node"},{"title":"Secret","body":"My secrets"},{"title":"Secretss","body":"My secrets"},{"title":"Secretsss","body":"My secrets"},{"title":"buy","body":"My secrets"},{"title":"tobuy","body":"My secrets"},{"title":"tobuyy","body":"My secrets"},{"title":"tobuyyy","body":"My secrets"},{"title":"HEllo","body":"World"},{"title":true},{"title":"flag title","body":"body"},{"title":"alias title","body":"alias body"},{"title":"tttt","body":"b"},{"title":"d","body":"s"},{"title":"New title","body":"New body"}]